{
	"ABI version": 2,
	"header": ["pubkey", "time"],
	"functions": [
		{
			"name": "constructor",
			"inputs": [
				{"name":"voters_set","type":"uint256[]"},
				{"name":"num_options","type":"uint64"}
			],
			"outputs": [
			]
		},
		{
			"name": "vote",
			"inputs": [
				{"name":"proof","type":"bytes"},
				{"name":"vote_choice","type":"uint32"},
				{"name":"vote_hmac","type":"uint256"},
				{"name":"anonymous_id","type":"uint256"}
			],
			"outputs": [
			]
		},
		{
			"name": "get_vote_set",
			"inputs": [
			],
			"outputs": [
				{"name":"value0","type":"uint256[]"}
			]
		},
		{
			"name": "get_results",
			"inputs": [
			],
			"outputs": [
				{"name":"results","type":"map(uint32,uint64)"}
			]
		},
		{
			"name": "get_vote",
			"inputs": [
				{"name":"anonymous_id","type":"uint256"}
			],
			"outputs": [
				{"name":"exists","type":"bool"},
				{"name":"vote_choice","type":"uint32"}
			]
		}
	],
	"data": [
	],
	"events": [
	]
}
